src/__init__.py
src/generate_MD_links.py
generate_md_links-0.1.2.dist-info/METADATA
generate_md_links-0.1.2.dist-info/WHEEL
generate_md_links-0.1.2.dist-info/entry_points.txt
generate_md_links-0.1.2.dist-info/top_level.txt
generate_md_links-0.1.2.dist-info/RECORD
