Metadata-Version: 2.1
Name: generate-md-links
Version: 0.1.2
Summary: Generate Markdown links for specified files.
Home-page: https://gitee.com/763593659/generate_-md_links
Author: xgh
